Workbook

Sheet Dataset
A1: order_id | B1: order_date | C1: ship_date | D1: ship_mode | E1: customer_name | F1: segment | G1: state | H1: country | I1: market | J1: region | K1: product_id | L1: category | M1: sub_category | N1: product_name | O1: sales | P1: quantity | Q1: discount | R1: profit | S1: shipping_cost | T1: order_priority | U1: year
A2: ES-2011-3848439 | B2: 40548 | C2: 40550 | D2: First Class | E2: Michael Granlund | F2: Home Office | G2: RhÃ´ne-Alpes | H2: France | I2: EU | J2: Central | K2: OFF-AR-10001291 | L2: Office Supplies | M2: Art | N2: Sanford Canvas, Fluorescent | O2: 207 | P2: 4 | Q2: 0 | R2: 76.56 | S2: 20.64 | T2: Medium | U2: 2011
A3: ES-2011-3848439 | B3: 40548 | C3: 40550 | D3: First Class | E3: Michael Granlund | F3: Home Office | G3: RhÃ´ne-Alpes | H3: France | I3: EU | J3: Central | K3: OFF-AR-10000833 | L3: Office Supplies | M3: Art | N3: Binney & Smith Pencil Sharpener, Water Color | O3: 90 | P3: 3 | Q3: 0 | R3: 20.52 | S3: 15.27 | T3: Medium | U3: 2011
A4: MZ-2011-1260 | B4: 40550 | C4: 40553 | D4: First Class | E4: Stewart Visinsky | F4: Consumer | G4: Niassa | H4: Mozambique | I4: Africa | J4: Africa | K4: OFF-ELD-10001694 | L4: Office Supplies | M4: Storage | N4: Eldon File Cart, Single Width | O4: 256 | P4: 2 | Q4: 0 | R4: 46.02 | S4: 52.46 | T4: High | U4: 2011
A5: ES-2011-5433855 | B5: 40550 | C5: 40551 | D5: First Class | E5: Dave Poirier | F5: Corporate | G5: Provence-Alpes-CÃ´te d'Azur | H5: France | I5: EU | J5: Central | K5: OFF-ST-10004855 | L5: Office Supplies | M5: Storage | N5: Smead Lockers, Industrial | O5: 716 | P5: 4 | Q5: 0.1 | R5: 143.16 | S5: 32.46 | T5: Medium | U5: 2011
A6: MZ-2011-1260 | B6: 40550 | C6: 40553 | D6: First Class | E6: Stewart Visinsky | F6: Consumer | G6: Niassa | H6: Mozambique | I6: Africa | J6: Africa | K6: OFF-STA-10004885 | L6: Office Supplies | M6: Art | N6: Stanley Sketch Pad, Easy-Erase | O6: 45 | P6: 1 | Q6: 0 | R6: 8.49 | S6: 13.7 | T6: High | U6: 2011
A7: ES-2011-5433855 | B7: 40550 | C7: 40551 | D7: First Class | E7: Dave Poirier | F7: Corporate | G7: Provence-Alpes-CÃ´te d'Azur | H7: France | I7: EU | J7: Central | K7: OFF-FA-10002071 | L7: Office Supplies | M7: Fasteners | N7: Accos Thumb Tacks, Assorted Sizes | O7: 33 | P7: 3 | Q7: 0 | R7: 2.25 | S7: 9.73 | T7: Medium | U7: 2011
A8: ES-2011-5433855 | B8: 40550 | C8: 40551 | D8: First Class | E8: Dave Poirier | F8: Corporate | G8: Provence-Alpes-CÃ´te d'Azur | H8: France | I8: EU | J8: Central | K8: FUR-BO-10000265 | L8: Furniture | M8: Bookcases | N8: Bush Floating Shelf Set, Pine | O8: 155 | P8: 1 | Q8: 0.1 | R8: 36.228 | S8: 5.72 | T8: Medium | U8: 2011
A9: CA-2011-106054 | B9: 40550 | C9: 40551 | D9: First Class | E9: Jack O'Briant | F9: Corporate | G9: Georgia | H9: United States | I9: US | J9: South | K9: OFF-AR-10002399 | L9: Office Supplies | M9: Art | N9: Dixon Prang Watercolor Pencils, 10-Color Set with Brush | O9: 13 | P9: 3 | Q9: 0 | R9: 5.2398 | S9: 3.51 | T9: Critical | U9: 2011
A10: IT-2011-5134922 | B10: 40550 | C10: 40553 | D10: First Class | E10: Joy Smith | F10: Consumer | G10: Groningen | H10: Netherlands | I10: EU | J10: Central | K10: OFF-AR-10000316 | L10: Office Supplies | M10: Art | N10: Stanley Pens, Blue | O10: 5 | P10: 1 | Q10: 0.5 | R10: -0.105 | S10: 0.28 | T10: Medium | U10: 2011
A11: IN-2011-79397 | B11: 40546 | C11: 40546 | D11: Same Day | E11: Kean Nguyen | F11: Corporate | G11: New South Wales | H11: Australia | I11: APAC | J11: Oceania | K11: OFF-AP-10000304 | L11: Office Supplies | M11: Appliances | N11: Hoover Microwave, White | O11: 276 | P11: 1 | Q11: 0.1 | R11: 110.412 | S11: 125.32 | T11: Critical | U11: 2011
A12: IN-2011-79397 | B12: 40546 | C12: 40546 | D12: Same Day | E12: Kean Nguyen | F12: Corporate | G12: New South Wales | H12: Australia | I12: APAC | J12: Oceania | K12: OFF-LA-10003396 | L12: Office Supplies | M12: Labels | N12: Avery Color Coded Labels, Laser Printer Compatible | O12: 36 | P12: 3 | Q12: 0.1 | R12: 4.743 | S12: 7.46 | T12: Critical | U12: 2011
A13: MX-2011-135629 | B13: 40550 | C13: 40550 | D13: Same Day | E13: Dorothy Dickinson | F13: Consumer | G13: SÃ£o Paulo | H13: Brazil | I13: LATAM | J13: South | K13: OFF-FA-10001871 | L13: Office Supplies | M13: Fasteners | N13: Stockwell Rubber Bands, Bulk Pack | O13: 43 | P13: 4 | Q13: 0 | R13: 6 | S13: 3.94 | T13: High | U13: 2011
... A100: ID-2011-46483 | B100: 40552 | C100: 40556 | D100: Standard Class | E100: Sample Company A | F100: Home Office | G100: Calabarzon | H100: Philippines | I100: APAC | J100: Southeast Asia | K100: OFF-PA-10003405 | L100: Office Supplies | M100: Paper | N100: Green Bar Memo Slips, Premium | O100: 9 | P100: 1 | Q100: 0.45 | R100: -1.7175 | S100: 0.69 | T100: High | U100: 2011

Sheet Dashboard
A1: Super-Store | Sales And Profit Dashboard
A4: Sales & Profit By Sub-Category | J4: Sales & Profit By Category
A23: Sales & Profit By Region | J23: Sales, Profit & Discount By Market

Sheet Analysis
A1: Data Cleaning
A3: Duplicate Value | C3: 0
A4: Missing value | C4: =COUNTBLANK(Dataset!O2:O100) -> 0
A6: Total Sales | C6: Total Profit | E6: Total Orders | G6: Average Discount
A7: =SUMPRODUCT(Dataset!O2:O100,Dataset!P2:P100) -> 141165 | C7: =SUM(Dataset!R2:R100) -> 2953.9984 | E7: =SUM(Dataset!P2:P100) -> 309 | G7: =AVERAGE(Dataset!Q2:Q100) -> 0.1649697
A9: Category | B9: Sales | C9: Profit
A10: Furniture | B10: =SUMIFS(Dataset!O2:O100,Dataset!L2:L100,"Furniture") -> 10431 | C10: =SUMIFS(Dataset!R2:R100,Dataset!L2:L100,"Furniture") -> 838.4827
A11: Office Supplies | B11: =SUMIFS(Dataset!O2:O100,Dataset!L2:L100,"Office Supplies") -> 9229 | C11: =SUMIFS(Dataset!R2:R100,Dataset!L2:L100,"Office Supplies") -> 1896.9276
A12: Technology | B12: =SUMIFS(Dataset!O2:O100,Dataset!L2:L100,"Technology") -> 7282 | C12: =SUMIFS(Dataset!R2:R100,Dataset!L2:L100,"Technology") -> 218.58814
A14: Sub-Category | B14: Sales | C14: Profit
A15: Tables | B15: =SUMIFS(Dataset!O2:O100,Dataset!M2:M100,"Tables") -> 211 | C15: =SUMIFS(Dataset!R2:R100,Dataset!M2:M100,"Tables") -> -70.3995
A16: Fasteners | B16: =SUMIFS(Dataset!O2:O100,Dataset!M2:M100,"Fasteners") -> 223 | C16: =SUMIFS(Dataset!R2:R100,Dataset!M2:M100,"Fasteners") -> -9.2285
A17: Labels | B17: =SUMIFS(Dataset!O2:O100,Dataset!M2:M100,"Labels") -> 138 | C17: =SUMIFS(Dataset!R2:R100,Dataset!M2:M100,"Labels") -> 46.0482
A18: Supplies | B18: =SUMIFS(Dataset!O2:O100,Dataset!M2:M100,"Supplies") -> 350 | C18: =SUMIFS(Dataset!R2:R100,Dataset!M2:M100,"Supplies") -> 90.956
A19: Envelopes | B19: =SUMIFS(Dataset!O2:O100,Dataset!M2:M100,"Envelopes") -> 377 | C19: =SUMIFS(Dataset!R2:R100,Dataset!M2:M100,"Envelopes") -> -66.396
A20: Furnishings | B20: =SUMIFS(Dataset!O2:O100,Dataset!M2:M100,"Furnishings") -> 590 | C20: =SUMIFS(Dataset!R2:R100,Dataset!M2:M100,"Furnishings") -> 50.0004
A21: Art | B21: =SUMIFS(Dataset!O2:O100,Dataset!M2:M100,"Art") -> 853 | C21: =SUMIFS(Dataset!R2:R100,Dataset!M2:M100,"Art") -> 80.8644
A22: Machines | B22: =SUMIFS(Dataset!O2:O100,Dataset!M2:M100,"Machines") -> 3321 | C22: =SUMIFS(Dataset!R2:R100,Dataset!M2:M100,"Machines") -> 153.0375
A23: Paper | B23: =SUMIFS(Dataset!O2:O100,Dataset!M2:M100,"Paper") -> 190 | C23: =SUMIFS(Dataset!R2:R100,Dataset!M2:M100,"Paper") -> 17.0496
A24: Binders | B24: =SUMIFS(Dataset!O2:O100,Dataset!M2:M100,"Binders") -> 704 | C24: =SUMIFS(Dataset!R2:R100,Dataset!M2:M100,"Binders") -> 271.0095
A25: Storage | B25: =SUMIFS(Dataset!O2:O100,Dataset!M2:M100,"Storage") -> 2966 | C25: =SUMIFS(Dataset!R2:R100,Dataset!M2:M100,"Storage") -> 313.9524
A26: Accessories | B26: =SUMIFS(Dataset!O2:O100,Dataset!M2:M100,"Accessories") -> 809 | C26: =SUMIFS(Dataset!R2:R100,Dataset!M2:M100,"Accessories") -> -169.8572
A27: Appliances | B27: =SUMIFS(Dataset!O2:O100,Dataset!M2:M100,"Appliances") -> 3428 | C27: =SUMIFS(Dataset!R2:R100,Dataset!M2:M100,"Appliances") -> 1152.672
A28: Chairs | B28: =SUMIFS(Dataset!O2:O100,Dataset!M2:M100,"Chairs") -> 3507 | C28: =SUMIFS(Dataset!R2:R100,Dataset!M2:M100,"Chairs") -> 884.5198
A29: Bookcases | B29: =SUMIFS(Dataset!O2:O100,Dataset!M2:M100,"Bookcases") -> 6123 | C29: =SUMIFS(Dataset!R2:R100,Dataset!M2:M100,"Bookcases") -> -25.638
A30: Phones | B30: =SUMIFS(Dataset!O2:O100,Dataset!M2:M100,"Phones") -> 1707 | C30: =SUMIFS(Dataset!R2:R100,Dataset!M2:M100,"Phones") -> 383.8536
A31: Copiers | B31: =SUMIFS(Dataset!O2:O100,Dataset!M2:M100,"Copiers") -> 1445 | C31: =SUMIFS(Dataset!R2:R100,Dataset!M2:M100,"Copiers") -> -148.44576

Sheet Pivot_Table
A1: Pivot Tables
A3: Category | B3: Sum of sales | C3: Sum of profit | E3: order_date | F3: (All)
A4: Furniture | B4: 10431 | C4: 838.4827
A5: Office Supplies | B5: 9229 | C5: 1896.9276 | E5: SubCategory | F5: Sum of sales | G5: Sum of profit
A6: Technology | B6: 7282 | C6: 218.58814 | E6: Accessories | F6: 809 | G6: -169.8572
A7: Grand Total | B7: 26942 | C7: 2953.9984 | E7: Appliances | F7: 3428 | G7: 1152.672
E8: Art | F8: 853 | G8: 80.8644
A9: country | B9: (All) | E9: Binders | F9: 704 | G9: 271.0095
E10: Bookcases | F10: 6123 | G10: -25.638
A11: Region | B11: Sum of sales | C11: Sum of profit | E11: Chairs | F11: 3507 | G11: 884.5198
A12: Africa | B12: 3414 | C12: 264.378 | E12: Copiers | F12: 1445 | G12: -148.44576
A13: Canada | B13: 314 | C13: 3.12 | E13: Envelopes | F13: 377 | G13: -66.396
A14: Caribbean | B14: 301 | C14: 20.4 | E14: Fasteners | F14: 223 | G14: -9.2285
A15: Central | B15: 3807 | C15: -616.854 | E15: Furnishings | F15: 590 | G15: 50.0004
A16: East | B16: 20 | C16: 4.884 | E16: Labels | F16: 138 | G16: 46.0482
A17: EMEA | B17: 1234 | C17: 442.41 | E17: Machines | F17: 3321 | G17: 153.0375
A18: North | B18: 4361 | C18: 1303.4932 | E18: Paper | F18: 190 | G18: 17.0496
A19: North Asia | B19: 2281 | C19: 310.53 | E19: Phones | F19: 1707 | G19: 383.8536
A20: Oceania | B20: 1810 | C20: -233.829 | E20: Storage | F20: 2966 | G20: 313.9524
A21: South | B21: 6321 | C21: 1887.2652 | E21: Supplies | F21: 350 | G21: 90.956
A22: Southeast Asia | B22: 3060 | C22: -441.1302 | E22: Tables | F22: 211 | G22: -70.3995
A23: West | B23: 19 | C23: 9.3312 | E23: Grand Total | F23: 26942 | G23: 2953.9984
A24: Grand Total | B24: 26942 | C24: 2953.9984
A26: Market | B26: Sum of sales | C26: Sum of discount | D26: Sum of profit
A27: Africa | B27: 3414 | C27: 0.7 | D27: 264.378
A28: APAC | B28: 7151 | C28: 8.73 | D28: -364.4292
A29: Canada | B29: 314 | C29: 0 | D29: 3.12
A30: EMEA | B30: 1234 | C30: 0 | D30: 442.41
A31: EU | B31: 3716 | C31: 3.3 | D31: -490.728
A32: LATAM | B32: 6294 | C32: 0.602 | D32: 1868.7122
A33: US | B33: 4819 | C33: 3 | D33: 1230.5354
A34: Grand Total | B34: 26942 | C34: 16.332 | D34: 2953.9984

Sheet Advance_Formulas
A1: Adavnce Formulas
A3: 1. Vlookup
A5: Order_Id | B5: ES-2011-5433855
A6: Customer_Name | B6: =IFERROR(VLOOKUP(B5,Dataset!A2:U100,5,FALSE),"Not Found") -> Dave Poirier
A7: Segment | B7: =IFERROR(VLOOKUP(B5,Dataset!A2:U100,6,FALSE),"Not Found") -> Corporate
A8: Country | B8: =IFERROR(VLOOKUP(B5,Dataset!A2:U100,8,FALSE),"Not Found") -> France
A9: Category | B9: =IFERROR(VLOOKUP(B5,Dataset!A2:U100,12,FALSE),"Not Found") -> Office Supplies
A10: Sales | B10: =IFERROR(VLOOKUP(B5,Dataset!A2:U100,15,FALSE),"Not Found") -> 716
A11: Profit | B11: =IFERROR(VLOOKUP(B5,Dataset!A2:U100,18,FALSE),"Not Found") -> 143.16
A13: 2. Index_Match
A15: Product_ID | B15: OFF-AR-10001291
A16: Product Name | B16: =INDEX(Dataset!K2:U100,MATCH(B15,Dataset!K2:K100,0),4) -> Sanford Canvas, Fluorescent
A17: Sub-Category | B17: =INDEX(Dataset!K2:U100,MATCH(Advance_Formulas!B15,Dataset!K2:K100,0),3) -> Art
A18: Sales | B18: =INDEX(Dataset!K2:U100,MATCH(Advance_Formulas!B15,Dataset!K2:K100,0),5) -> 207
